pycerberus/__init__.py
pycerberus/cli.py
pycerberus/client.py
pycerberus/models/clamav.py
pycerberus/models/common.py
pycerberus/models/die.py
pycerberus/models/extract.py
pycerberus/models/filter.py
pycerberus/models/gorille_dynamic.py
pycerberus/models/gorille_packer.py
pycerberus/models/gorille_sites_gcore.py
pycerberus/models/gorille_static.py
pycerberus/models/graph_3d.py
pycerberus/models/is_alive.py
pycerberus/models/load_db.py
pycerberus/models/load_db_gcore.py
pycerberus/models/magic.py
pycerberus/models/malware_metadata.py
pycerberus/models/naming.py
pycerberus/models/signature.py
pycerberus/models/status.py
pycerberus/models/strings.py
pycerberus/models/unload_db.py
pycerberus/models/unload_db_gcore.py
pycerberus/models/usage.py
pycerberus/models/version.py
pycerberus_cyd-0.1.2.dist-info/METADATA
pycerberus_cyd-0.1.2.dist-info/WHEEL
pycerberus_cyd-0.1.2.dist-info/entry_points.txt
pycerberus_cyd-0.1.2.dist-info/licenses/LICENSE.txt
pycerberus_cyd-0.1.2.dist-info/RECORD
