Metadata-Version: 2.4
Name: pycerberus-cyd
Version: 0.1.2
Summary: Python client and CLI for the Cerberus server
Author-email: Cyber-Detect <team@cyber-detect.com>
License-Expression: MIT
License-File: LICENSE.txt
Requires-Python: >=3.8
Requires-Dist: aiohttp==3.10.10
Requires-Dist: pydantic==2.9.2
Requires-Dist: requests==2.32
Requires-Dist: typer[all]
